personnamenorm/__init__.py
personnamenorm/namenorm.py
personnamenorm-0.2.dist-info/LICENSE
personnamenorm-0.2.dist-info/METADATA
personnamenorm-0.2.dist-info/WHEEL
personnamenorm-0.2.dist-info/top_level.txt
personnamenorm-0.2.dist-info/RECORD
