Metadata-Version: 2.1
Name: personnamenorm
Version: 0.2
Summary: unifying person names in different notations
Home-page: https://github.com/klauslippert/person-name-normalisation
Author: Klaus Lippert
Author-email: 
License: UNKNOWN
Platform: UNKNOWN
Classifier: Programming Language :: Python :: 3
Classifier: License :: OSI Approved :: MIT License
Classifier: Operating System :: OS Independent
Classifier: Topic :: Text Processing :: Linguistic
Requires-Dist: nltk (>=3.4)
Requires-Dist: ftfy (>=5.8)
